setup.py
ale_python_interface/__init__.py
ale_python_interface/ale_c_wrapper.cpp
ale_python_interface/ale_python_interface.py
ale_python_interface/libale_c.so
ale_python_interface.egg-info/PKG-INFO
ale_python_interface.egg-info/SOURCES.txt
ale_python_interface.egg-info/dependency_links.txt
ale_python_interface.egg-info/top_level.txt