Metadata-Version: 1.0
Name: ale-python-interface
Version: 0.0.1
Summary: Arcade Learning Environment Python Interface
Home-page: https://github.com/bbitmaster/ale_python_interface
Author: Ben Goodrich
Author-email: UNKNOWN
License: GPL
Platform: UNKNOWN
